ASAP/Solar_Calculation.py
ASAP/__init__.py
Solar_Calculation-0.1.dev0.dist-info/METADATA
Solar_Calculation-0.1.dev0.dist-info/RECORD
Solar_Calculation-0.1.dev0.dist-info/WHEEL
Solar_Calculation-0.1.dev0.dist-info/top_level.txt
