Metadata-Version: 2.1
Name: Solar-Calculation
Version: 0.1.dev0
Summary: UNKNOWN
Home-page: https://github.com/Yueningwang/ASAP
Author: UNKNOWN
Author-email: UNKNOWN
License: MIT
Platform: UNKNOWN
